[
  {
    "id": "1510101@01@Semester_1",
    "code": "1510101",
    "name": "Business Mathematics",
    "branchId": "01",
    "semester": 1,
    "courseCode": "BB",
    "semesterLabel": "Semester 1",
    "alternateCodes": [],
    "alternateIds": [],
    "slug": "business-mathematics"
  },
  {
    "id": "BB01001031@01@Semester_1",
    "code": "BB01001031",
    "name": "Business Statistics and Logic",
    "branchId": "01",
    "semester": 1,
    "courseCode": "BB",
    "semesterLabel": "Semester 1",
    "alternateCodes": [],
    "alternateIds": [],
    "slug": "business-statistics-and-logic"
  },
  {
    "id": "1510106@01@Semester_1",
    "code": "1510106",
    "name": "English Grammar and Composition",
    "branchId": "01",
    "semester": 1,
    "courseCode": "BB",
    "semesterLabel": "Semester 1",
    "alternateCodes": [],
    "alternateIds": [],
    "slug": "english-grammar-and-composition"
  },
  {
    "id": "BB01001021@01@Semester_1",
    "code": "BB01001021",
    "name": "Financial Accounting",
    "branchId": "01",
    "semester": 1,
    "courseCode": "BB",
    "semesterLabel": "Semester 1",
    "alternateCodes": [],
    "alternateIds": [],
    "slug": "financial-accounting"
  },
  {
    "id": "BB01001061@01@Semester_1",
    "code": "BB01001061",
    "name": "Fundamentals of ESG for Sustainability",
    "branchId": "01",
    "semester": 1,
    "courseCode": "BB",
    "semesterLabel": "Semester 1",
    "alternateCodes": [],
    "alternateIds": [],
    "slug": "fundamentals-of-esg-for-sustainability"
  },
  {
    "id": "1510104@01@Semester_1",
    "code": "1510104",
    "name": "Fundamentals of Financial Accounting",
    "branchId": "01",
    "semester": 1,
    "courseCode": "BB",
    "semesterLabel": "Semester 1",
    "alternateCodes": [],
    "alternateIds": [],
    "slug": "fundamentals-of-financial-accounting"
  },
  {
    "id": "1510103@01@Semester_1",
    "code": "1510103",
    "name": "Fundamentals of Information Technology",
    "branchId": "01",
    "semester": 1,
    "courseCode": "BB",
    "semesterLabel": "Semester 1",
    "alternateCodes": [],
    "alternateIds": [],
    "slug": "fundamentals-of-information-technology"
  },
  {
    "id": "BB01001041@01@Semester_1",
    "code": "BB01001041",
    "name": "General and Communicative English",
    "branchId": "01",
    "semester": 1,
    "courseCode": "BB",
    "semesterLabel": "Semester 1",
    "alternateCodes": [],
    "alternateIds": [],
    "slug": "general-and-communicative-english"
  },
  {
    "id": "1510105@01@Semester_1",
    "code": "1510105",
    "name": "Gujarati Culture and Business",
    "branchId": "01",
    "semester": 1,
    "courseCode": "BB",
    "semesterLabel": "Semester 1",
    "alternateCodes": [],
    "alternateIds": [],
    "slug": "gujarati-culture-and-business"
  },
  {
    "id": "BB01001051@01@Semester_1",
    "code": "BB01001051",
    "name": "Indian Knowledge Systems",
    "branchId": "01",
    "semester": 1,
    "courseCode": "BB",
    "semesterLabel": "Semester 1",
    "alternateCodes": [],
    "alternateIds": [],
    "slug": "indian-knowledge-systems"
  },
  {
    "id": "1510102@01@Semester_1",
    "code": "1510102",
    "name": "Microeconomics",
    "branchId": "01",
    "semester": 1,
    "courseCode": "BB",
    "semesterLabel": "Semester 1",
    "alternateCodes": [],
    "alternateIds": [],
    "slug": "microeconomics"
  },
  {
    "id": "BB01001011@01@Semester_1",
    "code": "BB01001011",
    "name": "Principles and Practices of Management",
    "branchId": "01",
    "semester": 1,
    "courseCode": "BB",
    "semesterLabel": "Semester 1",
    "alternateCodes": [],
    "alternateIds": [],
    "slug": "principles-and-practices-of-management"
  },
  {
    "id": "BB02001041@01@Semester_2",
    "code": "BB02001041",
    "name": "Business Communication",
    "branchId": "01",
    "semester": 2,
    "courseCode": "BB",
    "semesterLabel": "Semester 2",
    "alternateCodes": [],
    "alternateIds": [],
    "slug": "business-communication"
  },
  {
    "id": "BB02001011@01@Semester_2",
    "code": "BB02001011",
    "name": "Business Economics",
    "branchId": "01",
    "semester": 2,
    "courseCode": "BB",
    "semesterLabel": "Semester 2",
    "alternateCodes": [],
    "alternateIds": [],
    "slug": "business-economics"
  },
  {
    "id": "1520104@01@Semester_2",
    "code": "1520104",
    "name": "Business Statistics",
    "branchId": "01",
    "semester": 2,
    "courseCode": "BB",
    "semesterLabel": "Semester 2",
    "alternateCodes": [],
    "alternateIds": [],
    "slug": "business-statistics"
  },
  {
    "id": "1520102@01@Semester_2",
    "code": "1520102",
    "name": "Corporate Accounting",
    "branchId": "01",
    "semester": 2,
    "courseCode": "BB",
    "semesterLabel": "Semester 2",
    "alternateCodes": [],
    "alternateIds": [],
    "slug": "corporate-accounting"
  },
  {
    "id": "BB02001021@01@Semester_2",
    "code": "BB02001021",
    "name": "Cost Accounting",
    "branchId": "01",
    "semester": 2,
    "courseCode": "BB",
    "semesterLabel": "Semester 2",
    "alternateCodes": [],
    "alternateIds": [],
    "slug": "cost-accounting"
  },
  {
    "id": "BB02001061@01@Semester_2",
    "code": "BB02001061",
    "name": "Design Thinking and Innovation",
    "branchId": "01",
    "semester": 2,
    "courseCode": "BB",
    "semesterLabel": "Semester 2",
    "alternateCodes": [],
    "alternateIds": [],
    "slug": "design-thinking-and-innovation"
  },
  {
    "id": "BB02001031@01@Semester_2",
    "code": "BB02001031",
    "name": "Human Behaviour in Organisations",
    "branchId": "01",
    "semester": 2,
    "courseCode": "BB",
    "semesterLabel": "Semester 2",
    "alternateCodes": [],
    "alternateIds": [],
    "slug": "human-behaviour-in-organisations"
  },
  {
    "id": "1520105@01@Semester_2",
    "code": "1520105",
    "name": "Indian Business System",
    "branchId": "01",
    "semester": 2,
    "courseCode": "BB",
    "semesterLabel": "Semester 2",
    "alternateCodes": [],
    "alternateIds": [],
    "slug": "indian-business-system"
  },
  {
    "id": "1520101@01@Semester_2",
    "code": "1520101",
    "name": "Macro Economics",
    "branchId": "01",
    "semester": 2,
    "courseCode": "BB",
    "semesterLabel": "Semester 2",
    "alternateCodes": [],
    "alternateIds": [],
    "slug": "macro-economics"
  },
  {
    "id": "1520103@01@Semester_2",
    "code": "1520103",
    "name": "Management Information Systems",
    "branchId": "01",
    "semester": 2,
    "courseCode": "BB",
    "semesterLabel": "Semester 2",
    "alternateCodes": [],
    "alternateIds": [],
    "slug": "management-information-systems"
  },
  {
    "id": "1530106@01@Semester_3",
    "code": "1530106",
    "name": "Advanced Business Statistics",
    "branchId": "01",
    "semester": 3,
    "courseCode": "BB",
    "semesterLabel": "Semester 3",
    "alternateCodes": [],
    "alternateIds": [],
    "slug": "advanced-business-statistics"
  },
  {
    "id": "BB02001041@01@Semester_3",
    "code": "BB02001041",
    "name": "Business Communication",
    "branchId": "01",
    "semester": 3,
    "courseCode": "BB",
    "semesterLabel": "Semester 3",
    "alternateCodes": [],
    "alternateIds": [],
    "slug": "business-communication-sem-3"
  },
  {
    "id": "1530104@01@Semester_3",
    "code": "1530104",
    "name": "Business Law",
    "branchId": "01",
    "semester": 3,
    "courseCode": "BB",
    "semesterLabel": "Semester 3",
    "alternateCodes": [],
    "alternateIds": [],
    "slug": "business-law"
  },
  {
    "id": "BB01001031@01@Semester_3",
    "code": "BB01001031",
    "name": "Business Statistics and Logic",
    "branchId": "01",
    "semester": 3,
    "courseCode": "BB",
    "semesterLabel": "Semester 3",
    "alternateCodes": [],
    "alternateIds": [],
    "slug": "business-statistics-and-logic-sem-3"
  },
  {
    "id": "1530101@01@Semester_3",
    "code": "1530101",
    "name": "Cost Accounting",
    "branchId": "01",
    "semester": 3,
    "courseCode": "BB",
    "semesterLabel": "Semester 3",
    "alternateCodes": [],
    "alternateIds": [],
    "slug": "cost-accounting-sem-3"
  },
  {
    "id": "BB02001061@01@Semester_3",
    "code": "BB02001061",
    "name": "Design Thinking and Innovation",
    "branchId": "01",
    "semester": 3,
    "courseCode": "BB",
    "semesterLabel": "Semester 3",
    "alternateCodes": [],
    "alternateIds": [],
    "slug": "design-thinking-and-innovation-sem-3"
  },
  {
    "id": "BB03001051@01@Semester_3",
    "code": "BB03001051",
    "name": "Health and Wellness",
    "branchId": "01",
    "semester": 3,
    "courseCode": "BB",
    "semesterLabel": "Semester 3",
    "alternateCodes": [],
    "alternateIds": [],
    "slug": "health-and-wellness"
  },
  {
    "id": "BB02001031@01@Semester_3",
    "code": "BB02001031",
    "name": "Human Behaviour in Organisations",
    "branchId": "01",
    "semester": 3,
    "courseCode": "BB",
    "semesterLabel": "Semester 3",
    "alternateCodes": [],
    "alternateIds": [],
    "slug": "human-behaviour-in-organisations-sem-3"
  },
  {
    "id": "BB03001021@01@Semester_3",
    "code": "BB03001021",
    "name": "Human Resource Management",
    "branchId": "01",
    "semester": 3,
    "courseCode": "BB",
    "semesterLabel": "Semester 3",
    "alternateCodes": [],
    "alternateIds": [],
    "slug": "human-resource-management"
  },
  {
    "id": "1530105@01@Semester_3",
    "code": "1530105",
    "name": "Human Values and Professional Ethics",
    "branchId": "01",
    "semester": 3,
    "courseCode": "BB",
    "semesterLabel": "Semester 3",
    "alternateCodes": [],
    "alternateIds": [],
    "slug": "human-values-and-professional-ethics"
  },
  {
    "id": "BB03001061@01@Semester_3",
    "code": "BB03001061",
    "name": "Legal and Ethical Issues in Business",
    "branchId": "01",
    "semester": 3,
    "courseCode": "BB",
    "semesterLabel": "Semester 3",
    "alternateCodes": [],
    "alternateIds": [],
    "slug": "legal-and-ethical-issues-in-business"
  },
  {
    "id": "BB03001011@01@Semester_3",
    "code": "BB03001011",
    "name": "Management Accounting",
    "branchId": "01",
    "semester": 3,
    "courseCode": "BB",
    "semesterLabel": "Semester 3",
    "alternateCodes": [],
    "alternateIds": [],
    "slug": "management-accounting"
  },
  {
    "id": "BB03001031@01@Semester_3",
    "code": "BB03001031",
    "name": "Management Information System",
    "branchId": "01",
    "semester": 3,
    "courseCode": "BB",
    "semesterLabel": "Semester 3",
    "alternateCodes": [],
    "alternateIds": [],
    "slug": "management-information-system"
  },
  {
    "id": "1530103@01@Semester_3",
    "code": "1530103",
    "name": "Managerial Communication",
    "branchId": "01",
    "semester": 3,
    "courseCode": "BB",
    "semesterLabel": "Semester 3",
    "alternateCodes": [],
    "alternateIds": [],
    "slug": "managerial-communication"
  },
  {
    "id": "BB03001041@01@Semester_3",
    "code": "BB03001041",
    "name": "Marketing Management",
    "branchId": "01",
    "semester": 3,
    "courseCode": "BB",
    "semesterLabel": "Semester 3",
    "alternateCodes": [],
    "alternateIds": [],
    "slug": "marketing-management"
  },
  {
    "id": "1530102@01@Semester_3",
    "code": "1530102",
    "name": "Organizational Behaviour",
    "branchId": "01",
    "semester": 3,
    "courseCode": "BB",
    "semesterLabel": "Semester 3",
    "alternateCodes": [],
    "alternateIds": [],
    "slug": "organizational-behaviour"
  },
  {
    "id": "1540102@01@Semester_4",
    "code": "1540102",
    "name": "Basics of Marketing Management",
    "branchId": "01",
    "semester": 4,
    "courseCode": "BB",
    "semesterLabel": "Semester 4",
    "alternateCodes": [],
    "alternateIds": [],
    "slug": "basics-of-marketing-management"
  },
  {
    "id": "1540105@01@Semester_4",
    "code": "1540105",
    "name": "Basics of Production and Operation Management",
    "branchId": "01",
    "semester": 4,
    "courseCode": "BB",
    "semesterLabel": "Semester 4",
    "alternateCodes": [],
    "alternateIds": [],
    "slug": "basics-of-production-and-operation-management"
  },
  {
    "id": "1540106@01@Semester_4",
    "code": "1540106",
    "name": "Event Management",
    "branchId": "01",
    "semester": 4,
    "courseCode": "BB",
    "semesterLabel": "Semester 4",
    "alternateCodes": [],
    "alternateIds": [],
    "slug": "event-management"
  },
  {
    "id": "1540103@01@Semester_4",
    "code": "1540103",
    "name": "Fundamentals of Financial Management",
    "branchId": "01",
    "semester": 4,
    "courseCode": "BB",
    "semesterLabel": "Semester 4",
    "alternateCodes": [],
    "alternateIds": [],
    "slug": "fundamentals-of-financial-management"
  },
  {
    "id": "1540104@01@Semester_4",
    "code": "1540104",
    "name": "Introduction of Human Resource Management",
    "branchId": "01",
    "semester": 4,
    "courseCode": "BB",
    "semesterLabel": "Semester 4",
    "alternateCodes": [],
    "alternateIds": [],
    "slug": "introduction-of-human-resource-management"
  },
  {
    "id": "1540101@01@Semester_4",
    "code": "1540101",
    "name": "Management Accounting",
    "branchId": "01",
    "semester": 4,
    "courseCode": "BB",
    "semesterLabel": "Semester 4",
    "alternateCodes": [],
    "alternateIds": [],
    "slug": "management-accounting-sem-4"
  },
  {
    "id": "1550102@01@Semester_5",
    "code": "1550102",
    "name": "Advance Marketing Management",
    "branchId": "01",
    "semester": 5,
    "courseCode": "BB",
    "semesterLabel": "Semester 5",
    "alternateCodes": [],
    "alternateIds": [],
    "slug": "advance-marketing-management"
  },
  {
    "id": "1550105@01@Semester_5",
    "code": "1550105",
    "name": "Advance Production and Operation Management",
    "branchId": "01",
    "semester": 5,
    "courseCode": "BB",
    "semesterLabel": "Semester 5",
    "alternateCodes": [],
    "alternateIds": [],
    "slug": "advance-production-and-operation-management"
  },
  {
    "id": "1550103@01@Semester_5",
    "code": "1550103",
    "name": "Corporate Finance",
    "branchId": "01",
    "semester": 5,
    "courseCode": "BB",
    "semesterLabel": "Semester 5",
    "alternateCodes": [],
    "alternateIds": [],
    "slug": "corporate-finance"
  },
  {
    "id": "1550104@01@Semester_5",
    "code": "1550104",
    "name": "Human Resource Development",
    "branchId": "01",
    "semester": 5,
    "courseCode": "BB",
    "semesterLabel": "Semester 5",
    "alternateCodes": [],
    "alternateIds": [],
    "slug": "human-resource-development"
  },
  {
    "id": "1550106@01@Semester_5",
    "code": "1550106",
    "name": "Indian Financial System",
    "branchId": "01",
    "semester": 5,
    "courseCode": "BB",
    "semesterLabel": "Semester 5",
    "alternateCodes": [],
    "alternateIds": [],
    "slug": "indian-financial-system"
  },
  {
    "id": "1550108@01@Semester_5",
    "code": "1550108",
    "name": "Performance Management and Compensation",
    "branchId": "01",
    "semester": 5,
    "courseCode": "BB",
    "semesterLabel": "Semester 5",
    "alternateCodes": [],
    "alternateIds": [],
    "slug": "performance-management-and-compensation"
  },
  {
    "id": "1550101@01@Semester_5",
    "code": "1550101",
    "name": "Research Methodology",
    "branchId": "01",
    "semester": 5,
    "courseCode": "BB",
    "semesterLabel": "Semester 5",
    "alternateCodes": [],
    "alternateIds": [],
    "slug": "research-methodology"
  },
  {
    "id": "1550107@01@Semester_5",
    "code": "1550107",
    "name": "Sales Management and CRM",
    "branchId": "01",
    "semester": 5,
    "courseCode": "BB",
    "semesterLabel": "Semester 5",
    "alternateCodes": [],
    "alternateIds": [],
    "slug": "sales-management-and-crm"
  },
  {
    "id": "1560108@01@Semester_6",
    "code": "1560108",
    "name": "Digital Marketing",
    "branchId": "01",
    "semester": 6,
    "courseCode": "BB",
    "semesterLabel": "Semester 6",
    "alternateCodes": [],
    "alternateIds": [],
    "slug": "digital-marketing"
  },
  {
    "id": "1560103@01@Semester_6",
    "code": "1560103",
    "name": "Direct & Indirect Taxation",
    "branchId": "01",
    "semester": 6,
    "courseCode": "BB",
    "semesterLabel": "Semester 6",
    "alternateCodes": [],
    "alternateIds": [],
    "slug": "direct-and-indirect-taxation"
  },
  {
    "id": "1560104@01@Semester_6",
    "code": "1560104",
    "name": "Entrepreneurship",
    "branchId": "01",
    "semester": 6,
    "courseCode": "BB",
    "semesterLabel": "Semester 6",
    "alternateCodes": [],
    "alternateIds": [],
    "slug": "entrepreneurship"
  },
  {
    "id": "1560110@01@Semester_6",
    "code": "1560110",
    "name": "HR Competencies",
    "branchId": "01",
    "semester": 6,
    "courseCode": "BB",
    "semesterLabel": "Semester 6",
    "alternateCodes": [],
    "alternateIds": [],
    "slug": "hr-competencies"
  },
  {
    "id": "1560106@01@Semester_6",
    "code": "1560106",
    "name": "Indian Banking System",
    "branchId": "01",
    "semester": 6,
    "courseCode": "BB",
    "semesterLabel": "Semester 6",
    "alternateCodes": [],
    "alternateIds": [],
    "slug": "indian-banking-system"
  },
  {
    "id": "1560105@01@Semester_6",
    "code": "1560105",
    "name": "Management of Financial Services",
    "branchId": "01",
    "semester": 6,
    "courseCode": "BB",
    "semesterLabel": "Semester 6",
    "alternateCodes": [],
    "alternateIds": [],
    "slug": "management-of-financial-services"
  },
  {
    "id": "1560107@01@Semester_6",
    "code": "1560107",
    "name": "Services Marketing",
    "branchId": "01",
    "semester": 6,
    "courseCode": "BB",
    "semesterLabel": "Semester 6",
    "alternateCodes": [],
    "alternateIds": [],
    "slug": "services-marketing"
  },
  {
    "id": "1560109@01@Semester_6",
    "code": "1560109",
    "name": "Strategic Human Resources Management",
    "branchId": "01",
    "semester": 6,
    "courseCode": "BB",
    "semesterLabel": "Semester 6",
    "alternateCodes": [],
    "alternateIds": [],
    "slug": "strategic-human-resources-management"
  },
  {
    "id": "1560102@01@Semester_6",
    "code": "1560102",
    "name": "Strategic Management",
    "branchId": "01",
    "semester": 6,
    "courseCode": "BB",
    "semesterLabel": "Semester 6",
    "alternateCodes": [],
    "alternateIds": [],
    "slug": "strategic-management"
  }
]
